lectiomat/Lectiomat.py
lectiomat/__init__.py
mlw_lectiomat-0.2.0.dist-info/LICENSE
mlw_lectiomat-0.2.0.dist-info/METADATA
mlw_lectiomat-0.2.0.dist-info/WHEEL
mlw_lectiomat-0.2.0.dist-info/top_level.txt
mlw_lectiomat-0.2.0.dist-info/RECORD
