Metadata-Version: 2.1
Name: mlw-lectiomat
Version: 0.2.0
Summary: OCR System for the Medieval Latin Dictionary at the Bavarian Academy of Sciences and Humanities.
Author-email: Gilary Vera Nuñez <gilary.vera22@gmail.com>, Philipp Koch <P.Koch@campus.lmu.de>
Project-URL: repository, https://gitlab.lrz.de/ocr-projects/mlw-consulting-project
Requires-Python: >=3.9
License-File: LICENSE
Requires-Dist: omegaconf (==2.3.0)
Requires-Dist: opencv-python (>=4.7.0.72)
Requires-Dist: transformers (>=4.26.1)
Requires-Dist: torch (>=2.0.0)
Requires-Dist: numpy (>=1.23.5)
Requires-Dist: ultralyticsplus (>=0.0.28)
